{
  "version": 19,
  "sheets": [
    {
      "id": "sh1",
      "name": "WMS",
      "colNumber": 26,
      "rowNumber": 100,
      "rows": {},
      "cols": {},
      "merges": [],
      "cells": {
        "A1": {
          "content": "KOB WMS Dashboard"
        }
      },
      "conditionalFormats": [],
      "figures": [],
      "areGridLinesVisible": true,
      "isVisible": true
    }
  ],
  "styles": {},
  "formats": {},
  "borders": {},
  "revisionId": "START_REVISION",
  "settings": {},
  "pivots": {},
  "pivotNextId": 1,
  "lists": {},
  "listNextId": 1,
  "globalFilters": []
}